<?xml version="1.0" encoding="UTF-8"?>
<!DOCTYPE mapper PUBLIC "-//mybatis.org//DTD Mapper 3.0//EN" "http://mybatis.org/dtd/mybatis-3-mapper.dtd">
<mapper namespace="com.dcdy.vote.dao.VtCompanyMapper">
  <resultMap id="BaseResultMap" type="com.dcdy.vote.dao.VtCompany">
    <!--
      WARNING - @mbggenerated
      This element is automatically generated by MyBatis Generator, do not modify.
      This element was generated on Mon Nov 21 19:55:12 CST 2016.
    -->
    <id column="id" jdbcType="INTEGER" property="id" />
    <result column="company_name" jdbcType="VARCHAR" property="companyName" />
    <result column="category_id" jdbcType="INTEGER" property="categoryId" />
    <result column="vote_num" jdbcType="INTEGER" property="voteNum" />
    <result column="company_image" jdbcType="VARCHAR" property="companyImage" />
    <result column="status" jdbcType="INTEGER" property="status" />
    <result column="concat_name" jdbcType="VARCHAR" property="concatName" />
    <result column="concat_mobile" jdbcType="VARCHAR" property="concatMobile" />
    <result column="position" jdbcType="INTEGER" property="position" />
    <result column="client_id" jdbcType="VARCHAR" property="clientId" />
  </resultMap>
  <sql id="Example_Where_Clause">
    <!--
      WARNING - @mbggenerated
      This element is automatically generated by MyBatis Generator, do not modify.
      This element was generated on Mon Nov 21 19:55:12 CST 2016.
    -->
    <where>
      <foreach collection="oredCriteria" item="criteria" separator="or">
        <if test="criteria.valid">
          <trim prefix="(" prefixOverrides="and" suffix=")">
            <foreach collection="criteria.criteria" item="criterion">
              <choose>
                <when test="criterion.noValue">
                  and ${criterion.condition}
                </when>
                <when test="criterion.singleValue">
                  and ${criterion.condition} #{criterion.value}
                </when>
                <when test="criterion.betweenValue">
                  and ${criterion.condition} #{criterion.value} and #{criterion.secondValue}
                </when>
                <when test="criterion.listValue">
                  and ${criterion.condition}
                  <foreach close=")" collection="criterion.value" item="listItem" open="(" separator=",">
                    #{listItem}
                  </foreach>
                </when>
              </choose>
            </foreach>
          </trim>
        </if>
      </foreach>
    </where>
  </sql>
  <sql id="Update_By_Example_Where_Clause">
    <!--
      WARNING - @mbggenerated
      This element is automatically generated by MyBatis Generator, do not modify.
      This element was generated on Mon Nov 21 19:55:12 CST 2016.
    -->
    <where>
      <foreach collection="example.oredCriteria" item="criteria" separator="or">
        <if test="criteria.valid">
          <trim prefix="(" prefixOverrides="and" suffix=")">
            <foreach collection="criteria.criteria" item="criterion">
              <choose>
                <when test="criterion.noValue">
                  and ${criterion.condition}
                </when>
                <when test="criterion.singleValue">
                  and ${criterion.condition} #{criterion.value}
                </when>
                <when test="criterion.betweenValue">
                  and ${criterion.condition} #{criterion.value} and #{criterion.secondValue}
                </when>
                <when test="criterion.listValue">
                  and ${criterion.condition}
                  <foreach close=")" collection="criterion.value" item="listItem" open="(" separator=",">
                    #{listItem}
                  </foreach>
                </when>
              </choose>
            </foreach>
          </trim>
        </if>
      </foreach>
    </where>
  </sql>
  <sql id="Base_Column_List">
    <!--
      WARNING - @mbggenerated
      This element is automatically generated by MyBatis Generator, do not modify.
      This element was generated on Mon Nov 21 19:55:12 CST 2016.
    -->
    id, company_name, category_id, vote_num, company_image, status, concat_name, concat_mobile, 
    position, client_id
  </sql>
  <select id="selectByExample" parameterType="com.dcdy.vote.dao.VtCompanyExample" resultMap="BaseResultMap">
    <!--
      WARNING - @mbggenerated
      This element is automatically generated by MyBatis Generator, do not modify.
      This element was generated on Mon Nov 21 19:55:12 CST 2016.
    -->
    select
    <if test="distinct">
      distinct
    </if>
    <include refid="Base_Column_List" />
    from vt_company
    <if test="_parameter != null">
      <include refid="Example_Where_Clause" />
    </if>
    <if test="orderByClause != null">
      order by ${orderByClause}
    </if>
    <if test="limitStart != null and limitStart&gt;=0">
      limit #{limitStart} , #{limitEnd}
    </if>
  </select>
  <select id="selectByPrimaryKey" parameterType="java.lang.Integer" resultMap="BaseResultMap">
    <!--
      WARNING - @mbggenerated
      This element is automatically generated by MyBatis Generator, do not modify.
      This element was generated on Mon Nov 21 19:55:12 CST 2016.
    -->
    select 
    <include refid="Base_Column_List" />
    from vt_company
    where id = #{id,jdbcType=INTEGER}
  </select>
  <delete id="deleteByPrimaryKey" parameterType="java.lang.Integer">
    <!--
      WARNING - @mbggenerated
      This element is automatically generated by MyBatis Generator, do not modify.
      This element was generated on Mon Nov 21 19:55:12 CST 2016.
    -->
    delete from vt_company
    where id = #{id,jdbcType=INTEGER}
  </delete>
  <delete id="deleteByExample" parameterType="com.dcdy.vote.dao.VtCompanyExample">
    <!--
      WARNING - @mbggenerated
      This element is automatically generated by MyBatis Generator, do not modify.
      This element was generated on Mon Nov 21 19:55:12 CST 2016.
    -->
    delete from vt_company
    <if test="_parameter != null">
      <include refid="Example_Where_Clause" />
    </if>
  </delete>
  <insert id="insert" parameterType="com.dcdy.vote.dao.VtCompany">
    <!--
      WARNING - @mbggenerated
      This element is automatically generated by MyBatis Generator, do not modify.
      This element was generated on Mon Nov 21 19:55:12 CST 2016.
    -->
    <selectKey keyProperty="id" order="AFTER" resultType="java.lang.Integer">
      SELECT LAST_INSERT_ID()
    </selectKey>
    insert into vt_company (company_name, category_id, vote_num, 
      company_image, status, concat_name, 
      concat_mobile, position, client_id
      )
    values (#{companyName,jdbcType=VARCHAR}, #{categoryId,jdbcType=INTEGER}, #{voteNum,jdbcType=INTEGER}, 
      #{companyImage,jdbcType=VARCHAR}, #{status,jdbcType=INTEGER}, #{concatName,jdbcType=VARCHAR}, 
      #{concatMobile,jdbcType=VARCHAR}, #{position,jdbcType=INTEGER}, #{clientId,jdbcType=VARCHAR}
      )
  </insert>
  <insert id="insertSelective" parameterType="com.dcdy.vote.dao.VtCompany">
    <!--
      WARNING - @mbggenerated
      This element is automatically generated by MyBatis Generator, do not modify.
      This element was generated on Mon Nov 21 19:55:12 CST 2016.
    -->
    <selectKey keyProperty="id" order="AFTER" resultType="java.lang.Integer">
      SELECT LAST_INSERT_ID()
    </selectKey>
    insert into vt_company
    <trim prefix="(" suffix=")" suffixOverrides=",">
      <if test="companyName != null">
        company_name,
      </if>
      <if test="categoryId != null">
        category_id,
      </if>
      <if test="voteNum != null">
        vote_num,
      </if>
      <if test="companyImage != null">
        company_image,
      </if>
      <if test="status != null">
        status,
      </if>
      <if test="concatName != null">
        concat_name,
      </if>
      <if test="concatMobile != null">
        concat_mobile,
      </if>
      <if test="position != null">
        position,
      </if>
      <if test="clientId != null">
        client_id,
      </if>
    </trim>
    <trim prefix="values (" suffix=")" suffixOverrides=",">
      <if test="companyName != null">
        #{companyName,jdbcType=VARCHAR},
      </if>
      <if test="categoryId != null">
        #{categoryId,jdbcType=INTEGER},
      </if>
      <if test="voteNum != null">
        #{voteNum,jdbcType=INTEGER},
      </if>
      <if test="companyImage != null">
        #{companyImage,jdbcType=VARCHAR},
      </if>
      <if test="status != null">
        #{status,jdbcType=INTEGER},
      </if>
      <if test="concatName != null">
        #{concatName,jdbcType=VARCHAR},
      </if>
      <if test="concatMobile != null">
        #{concatMobile,jdbcType=VARCHAR},
      </if>
      <if test="position != null">
        #{position,jdbcType=INTEGER},
      </if>
      <if test="clientId != null">
        #{clientId,jdbcType=VARCHAR},
      </if>
    </trim>
  </insert>
  <select id="countByExample" parameterType="com.dcdy.vote.dao.VtCompanyExample" resultType="java.lang.Integer">
    <!--
      WARNING - @mbggenerated
      This element is automatically generated by MyBatis Generator, do not modify.
      This element was generated on Mon Nov 21 19:55:12 CST 2016.
    -->
    select count(*) from vt_company
    <if test="_parameter != null">
      <include refid="Example_Where_Clause" />
    </if>
  </select>
  <update id="updateByExampleSelective" parameterType="map">
    <!--
      WARNING - @mbggenerated
      This element is automatically generated by MyBatis Generator, do not modify.
      This element was generated on Mon Nov 21 19:55:12 CST 2016.
    -->
    update vt_company
    <set>
      <if test="record.id != null">
        id = #{record.id,jdbcType=INTEGER},
      </if>
      <if test="record.companyName != null">
        company_name = #{record.companyName,jdbcType=VARCHAR},
      </if>
      <if test="record.categoryId != null">
        category_id = #{record.categoryId,jdbcType=INTEGER},
      </if>
      <if test="record.voteNum != null">
        vote_num = #{record.voteNum,jdbcType=INTEGER},
      </if>
      <if test="record.companyImage != null">
        company_image = #{record.companyImage,jdbcType=VARCHAR},
      </if>
      <if test="record.status != null">
        status = #{record.status,jdbcType=INTEGER},
      </if>
      <if test="record.concatName != null">
        concat_name = #{record.concatName,jdbcType=VARCHAR},
      </if>
      <if test="record.concatMobile != null">
        concat_mobile = #{record.concatMobile,jdbcType=VARCHAR},
      </if>
      <if test="record.position != null">
        position = #{record.position,jdbcType=INTEGER},
      </if>
      <if test="record.clientId != null">
        client_id = #{record.clientId,jdbcType=VARCHAR},
      </if>
    </set>
    <if test="_parameter != null">
      <include refid="Update_By_Example_Where_Clause" />
    </if>
  </update>
  <update id="updateByExample" parameterType="map">
    <!--
      WARNING - @mbggenerated
      This element is automatically generated by MyBatis Generator, do not modify.
      This element was generated on Mon Nov 21 19:55:12 CST 2016.
    -->
    update vt_company
    set id = #{record.id,jdbcType=INTEGER},
      company_name = #{record.companyName,jdbcType=VARCHAR},
      category_id = #{record.categoryId,jdbcType=INTEGER},
      vote_num = #{record.voteNum,jdbcType=INTEGER},
      company_image = #{record.companyImage,jdbcType=VARCHAR},
      status = #{record.status,jdbcType=INTEGER},
      concat_name = #{record.concatName,jdbcType=VARCHAR},
      concat_mobile = #{record.concatMobile,jdbcType=VARCHAR},
      position = #{record.position,jdbcType=INTEGER},
      client_id = #{record.clientId,jdbcType=VARCHAR}
    <if test="_parameter != null">
      <include refid="Update_By_Example_Where_Clause" />
    </if>
  </update>
  <update id="updateByPrimaryKeySelective" parameterType="com.dcdy.vote.dao.VtCompany">
    <!--
      WARNING - @mbggenerated
      This element is automatically generated by MyBatis Generator, do not modify.
      This element was generated on Mon Nov 21 19:55:12 CST 2016.
    -->
    update vt_company
    <set>
      <if test="companyName != null">
        company_name = #{companyName,jdbcType=VARCHAR},
      </if>
      <if test="categoryId != null">
        category_id = #{categoryId,jdbcType=INTEGER},
      </if>
      <if test="voteNum != null">
        vote_num = #{voteNum,jdbcType=INTEGER},
      </if>
      <if test="companyImage != null">
        company_image = #{companyImage,jdbcType=VARCHAR},
      </if>
      <if test="status != null">
        status = #{status,jdbcType=INTEGER},
      </if>
      <if test="concatName != null">
        concat_name = #{concatName,jdbcType=VARCHAR},
      </if>
      <if test="concatMobile != null">
        concat_mobile = #{concatMobile,jdbcType=VARCHAR},
      </if>
      <if test="position != null">
        position = #{position,jdbcType=INTEGER},
      </if>
      <if test="clientId != null">
        client_id = #{clientId,jdbcType=VARCHAR},
      </if>
    </set>
    where id = #{id,jdbcType=INTEGER}
  </update>
  <update id="updateByPrimaryKey" parameterType="com.dcdy.vote.dao.VtCompany">
    <!--
      WARNING - @mbggenerated
      This element is automatically generated by MyBatis Generator, do not modify.
      This element was generated on Mon Nov 21 19:55:12 CST 2016.
    -->
    update vt_company
    set company_name = #{companyName,jdbcType=VARCHAR},
      category_id = #{categoryId,jdbcType=INTEGER},
      vote_num = #{voteNum,jdbcType=INTEGER},
      company_image = #{companyImage,jdbcType=VARCHAR},
      status = #{status,jdbcType=INTEGER},
      concat_name = #{concatName,jdbcType=VARCHAR},
      concat_mobile = #{concatMobile,jdbcType=VARCHAR},
      position = #{position,jdbcType=INTEGER},
      client_id = #{clientId,jdbcType=VARCHAR}
    where id = #{id,jdbcType=INTEGER}
  </update>
</mapper>